LICENCE
README
setup.py
finraph.egg-info/PKG-INFO
finraph.egg-info/SOURCES.txt
finraph.egg-info/dependency_links.txt
finraph.egg-info/top_level.txt
src/__init__.py
src/finraph.py