Metadata-Version: 2.1
Name: finraph
Version: 0.0.1
Summary: Graph analysis on Traded Companies
Home-page: UNKNOWN
Author: ROhit Gupta
Author-email: gupta.rohit21198@gmail.com
License: MIT
Keywords: finance graphs
Platform: UNKNOWN
Classifier: Development Status :: 5 - Production/Stable
Classifier: Intended Audience :: Education
Classifier: License :: OSI Approved :: MIT License
Classifier: Programming Language :: Python :: 3
License-File: LICENCE
